ros_stereo_msgs-5.5.1.data/data/include/stereo_msgs/stereo_msgs/msg/disparity_image.h
ros_stereo_msgs-5.5.1.data/data/include/stereo_msgs/stereo_msgs/msg/disparity_image.hpp
ros_stereo_msgs-5.5.1.data/data/include/stereo_msgs/stereo_msgs/msg/rosidl_generator_c__visibility_control.h
ros_stereo_msgs-5.5.1.data/data/include/stereo_msgs/stereo_msgs/msg/rosidl_generator_cpp__visibility_control.hpp
ros_stereo_msgs-5.5.1.data/data/include/stereo_msgs/stereo_msgs/msg/rosidl_typesupport_fastrtps_c__visibility_control.h
ros_stereo_msgs-5.5.1.data/data/include/stereo_msgs/stereo_msgs/msg/rosidl_typesupport_fastrtps_cpp__visibility_control.h
ros_stereo_msgs-5.5.1.data/data/include/stereo_msgs/stereo_msgs/msg/rosidl_typesupport_introspection_c__visibility_control.h
ros_stereo_msgs-5.5.1.data/data/include/stereo_msgs/stereo_msgs/msg/detail/disparity_image__builder.hpp
ros_stereo_msgs-5.5.1.data/data/include/stereo_msgs/stereo_msgs/msg/detail/disparity_image__description.c
ros_stereo_msgs-5.5.1.data/data/include/stereo_msgs/stereo_msgs/msg/detail/disparity_image__functions.c
ros_stereo_msgs-5.5.1.data/data/include/stereo_msgs/stereo_msgs/msg/detail/disparity_image__functions.h
ros_stereo_msgs-5.5.1.data/data/include/stereo_msgs/stereo_msgs/msg/detail/disparity_image__rosidl_typesupport_fastrtps_c.h
ros_stereo_msgs-5.5.1.data/data/include/stereo_msgs/stereo_msgs/msg/detail/disparity_image__rosidl_typesupport_fastrtps_cpp.hpp
ros_stereo_msgs-5.5.1.data/data/include/stereo_msgs/stereo_msgs/msg/detail/disparity_image__rosidl_typesupport_introspection_c.h
ros_stereo_msgs-5.5.1.data/data/include/stereo_msgs/stereo_msgs/msg/detail/disparity_image__rosidl_typesupport_introspection_cpp.hpp
ros_stereo_msgs-5.5.1.data/data/include/stereo_msgs/stereo_msgs/msg/detail/disparity_image__struct.h
ros_stereo_msgs-5.5.1.data/data/include/stereo_msgs/stereo_msgs/msg/detail/disparity_image__struct.hpp
ros_stereo_msgs-5.5.1.data/data/lib/python3.13/site-packages/stereo_msgs-5.5.1-py3.13.egg-info/PKG-INFO
ros_stereo_msgs-5.5.1.data/data/lib/python3.13/site-packages/stereo_msgs-5.5.1-py3.13.egg-info/SOURCES.txt
ros_stereo_msgs-5.5.1.data/data/lib/python3.13/site-packages/stereo_msgs-5.5.1-py3.13.egg-info/dependency_links.txt
ros_stereo_msgs-5.5.1.data/data/lib/python3.13/site-packages/stereo_msgs-5.5.1-py3.13.egg-info/top_level.txt
ros_stereo_msgs-5.5.1.dist-info/METADATA
ros_stereo_msgs-5.5.1.dist-info/WHEEL
ros_stereo_msgs-5.5.1.dist-info/top_level.txt
ros_stereo_msgs-5.5.1.dist-info/RECORD
ros_stereo_msgs-5.5.1.dist-info/licenses/LICENSE
