Metadata-Version: 2.4
Name: ros-stereo-msgs
Version: 5.5.1
Summary: ROS package 'stereo_msgs' provides messages for describing a disparity image, specifically the DisparityImage message type.
License-File: LICENSE
Requires-Dist: ros-std-msgs~=5.5.1
Requires-Dist: ros-rosidl-default-runtime~=1.7.1
Requires-Dist: ros-sensor-msgs~=5.5.1
Dynamic: description
Dynamic: description-content-type
Dynamic: license-file
Dynamic: requires-dist
Dynamic: summary
